canalysis/__init__.py
canalysis/analysis/__init__.py
canalysis/analysis/principal_components.py
canalysis/analysis/process_data.py
canalysis/analysis/analysis_utils/__init__.py
canalysis/analysis/analysis_utils/analysis_funcs.py
canalysis/data/__init__.py
canalysis/data/containers/__init__.py
canalysis/data/containers/all_data.py
canalysis/data/containers/calcium_data.py
canalysis/data/containers/eating_data.py
canalysis/data/containers/event_data.py
canalysis/data/containers/gpio_data.py
canalysis/data/containers/taste_data.py
canalysis/data/containers/trace_data.py
canalysis/data/data_utils/__init__.py
canalysis/data/data_utils/displayable_path.py
canalysis/data/data_utils/file_handler.py
canalysis/graphs/__init__.py
canalysis/graphs/heatmaps.py
canalysis/graphs/plot.py
canalysis/graphs/base/__init__.py
canalysis/graphs/base/_base_figure.py
canalysis/graphs/base/_base_heatmap.py
canalysis/graphs/graph_utils/Mixins.py
canalysis/graphs/graph_utils/__init__.py
canalysis/graphs/graph_utils/ax_helpers.py
canalysis/graphs/graph_utils/helpers.py
canalysis/graphs/graph_utils/quick_plots.py
canalysis/helpers/__init__.py
canalysis/helpers/excepts.py
canalysis/helpers/funcs.py
canalysis/helpers/wrappers.py
canalysis/neuralnetwork/SVM.py
canalysis/neuralnetwork/__init__.py
canalysis/neuralnetwork/nn_utils/__init__.py
canalysis/neuralnetwork/nn_utils/_properties.py
canalysis/neuralnetwork/nn_utils/_validate.py
canalysis/neuralnetwork/nn_utils/datahandler.py
canalysis/neuralnetwork/nn_utils/funcs.py
canalysis/neuralnetwork/nn_utils/scores.py
canalysis/parameters/__init__.py
canalysis-1.0.0.dist-info/LICENSE
canalysis-1.0.0.dist-info/METADATA
canalysis-1.0.0.dist-info/WHEEL
canalysis-1.0.0.dist-info/top_level.txt
canalysis-1.0.0.dist-info/RECORD
