Metadata-Version: 2.1
Name: canalysis
Version: 1.0.0
Summary: This project provides a structure to integrate calcium traces and events, perform statistical analysis, make graphs and do classification problems to further understand the dataset.
Author: Flynn OConnell
Author-email: Flynn OConnell <FlynnOConnell@gmail.com>
License: MIT License
Project-URL: Homepage, https://github.com/NeuroPyPy/canalysis
Keywords: feed,reader,tutorial
Platform: any
Classifier: Programming Language :: Python :: 3
Classifier: License :: OSI Approved :: MIT License
Classifier: Operating System :: OS Independent
Requires-Python: >=3.0
License-File: LICENSE
Requires-Dist: python-dateutil (>=2.8.1)
Requires-Dist: pytz (>=2020.1)
Requires-Dist: numpy (>=1.18.5) ; platform_machine != "aarch64" and platform_machine != "arm64" and python_version < "3.10"
Requires-Dist: numpy (>=1.19.2) ; platform_machine == "aarch64" and python_version < "3.10"
Requires-Dist: numpy (>=1.20.0) ; platform_machine == "arm64" and python_version < "3.10"
Requires-Dist: numpy (>=1.21.0) ; python_version >= "3.10"
Provides-Extra: testing
Requires-Dist: pytest (>=6.0) ; extra == 'testing'
Requires-Dist: pytest-cov (>=2.0) ; extra == 'testing'
Requires-Dist: mypy (>=0.910) ; extra == 'testing'
Requires-Dist: flake8 (>=3.9) ; extra == 'testing'
Requires-Dist: tox (>=3.24) ; extra == 'testing'
